scripts/__init__.py
scripts/main.py
scripts/util.py
python_alias-0.0.6.dist-info/METADATA
python_alias-0.0.6.dist-info/WHEEL
python_alias-0.0.6.dist-info/entry_points.txt
python_alias-0.0.6.dist-info/top_level.txt
python_alias-0.0.6.dist-info/RECORD
